COPYING
COPYING.LESSER
MANIFEST.in
README.rst
VERSION
__init__.py
libarray_ptr.py
requirements.setup.txt
requirements.txt
setup.py
zetuprc
./__init__.py
./libarray_ptr.py
include/array_ptr.hpp
include/array_ptr/array_ptr.hpp
include/array_ptr/const_array_ptr.hpp
include/array_ptr/array_ptr.hpp
include/array_ptr/const_array_ptr.hpp
libarray_ptr.egg-info/PKG-INFO
libarray_ptr.egg-info/SOURCES.txt
libarray_ptr.egg-info/dependency_links.txt
libarray_ptr.egg-info/requires.txt
libarray_ptr.egg-info/top_level.txt