Metadata-Version: 1.1
Name: libarray-ptr
Version: 0.12
Summary: C++ wrapper for C arrays with STL features
Home-page: http://bitbucket.org/StefanZimmermann/array_ptr
Author: Stefan Zimmermann
Author-email: zimmermann.code@gmail.com
License: LGPLv3
Platform: UNKNOWN
Classifier: Programming Language :: Python
